setup.py
cmd_line/__init__.py
cmd_line/autoencoders/__init__.py
cmd_line/autoencoders/run_autoencoder.py
cmd_line/autoencoders/run_stacked_autoencoder_supervised.py
cmd_line/autoencoders/run_stacked_autoencoder_unsupervised.py
cmd_line/boltzmann/__init__.py
cmd_line/boltzmann/run_dbn.py
cmd_line/boltzmann/run_deep_autoencoder.py
cmd_line/boltzmann/run_rbm.py
cmd_line/convolutional/__init__.py
cmd_line/convolutional/run_conv_net.py
cmd_line/linear/__init__.py
cmd_line/linear/run_logistic_regression.py
cmd_line/recurrent/__init__.py
cmd_line/recurrent/run_lstm.py
yadlt/__init__.py
yadlt.egg-info/PKG-INFO
yadlt.egg-info/SOURCES.txt
yadlt.egg-info/dependency_links.txt
yadlt.egg-info/not-zip-safe
yadlt.egg-info/top_level.txt
yadlt/core/__init__.py
yadlt/core/config.py
yadlt/core/layers.py
yadlt/core/model.py
yadlt/core/supervised_model.py
yadlt/core/trainers.py
yadlt/core/unsupervised_model.py
yadlt/models/__init__.py
yadlt/models/autoencoders/__init__.py
yadlt/models/autoencoders/deep_autoencoder.py
yadlt/models/autoencoders/denoising_autoencoder.py
yadlt/models/autoencoders/stacked_denoising_autoencoder.py
yadlt/models/boltzmann/__init__.py
yadlt/models/boltzmann/dbn.py
yadlt/models/boltzmann/deep_autoencoder.py
yadlt/models/boltzmann/rbm.py
yadlt/models/convolutional/__init__.py
yadlt/models/convolutional/conv_net.py
yadlt/models/linear/__init__.py
yadlt/models/linear/logistic_regression.py
yadlt/models/recurrent/__init__.py
yadlt/models/recurrent/lstm.py
yadlt/utils/__init__.py
yadlt/utils/datasets.py
yadlt/utils/tf_utils.py
yadlt/utils/utilities.py