Metadata-Version: 1.1
Name: yadlt
Version: 0.0.6
Summary: Implementation of various deep learning algorithms using Tensorflow. Class interfaces is sklearn-like.
Home-page: https://github.com/blackecho/Deep-Learning-Tensorflow
Author: Gabriele Angeletti
Author-email: angeletti.gabriele@gmail.com
License: MIT
Download-URL: https://github.com/blackecho/Deep-Learning-TensorFlow/tarball/0.0.6
Platform: any
